paretoarchive/__init__.py
paretoarchive/np.py
paretoarchive/pandas.py
py_paretoarchive-1.0.dist-info/licenses/LICENSE
py_paretoarchive-1.0.dist-info/METADATA
py_paretoarchive-1.0.dist-info/WHEEL
py_paretoarchive-1.0.dist-info/top_level.txt
py_paretoarchive-1.0.dist-info/RECORD
