Metadata-Version: 2.4
Name: py-paretoarchive
Version: 1.0
Summary: Efficient incremental Pareto archive based on BSP
Home-page: https://github.com/ehw-fit/py-paretoarchive
Author: Zdenek Vasicek
Author-email: Vojtech Mrazek <mrazek@fit.vutbr.cz>
License: MIT
Project-URL: Homepage, https://github.com/ehw-fit/py-paretoarchive
Project-URL: Repository, https://github.com/ehw-fit/py-paretoarchive
Project-URL: Issue Tracker, https://github.com/ehw-fit/py-paretoarchive/issues
Project-URL: Download, https://pypi.org/project/py-paretoarchive
Classifier: Development Status :: 1 - Planning
Classifier: License :: OSI Approved :: MIT License
Classifier: Intended Audience :: Education
Classifier: Intended Audience :: Science/Research
Classifier: Topic :: Scientific/Engineering
Classifier: Topic :: Scientific/Engineering :: Mathematics
Classifier: Natural Language :: English
Classifier: Operating System :: OS Independent
Classifier: Programming Language :: C
Classifier: Programming Language :: Python
Classifier: Programming Language :: Python :: 3
Requires-Python: >=3.8
License-File: LICENSE
Dynamic: license-file
